pylytics/__init__.py
pylytics/base.py
pylytics/integrator.py
databuff-0.1.2.dist-info/METADATA
databuff-0.1.2.dist-info/WHEEL
databuff-0.1.2.dist-info/RECORD
