Metadata-Version: 2.1
Name: databuff
Version: 0.1.2
Summary: 
Author: tekritesh
Author-email: ritesh.tekriwal03@gmail.com
Requires-Python: >=3.10,<4.0
Classifier: Programming Language :: Python :: 3
Classifier: Programming Language :: Python :: 3.10
Classifier: Programming Language :: Python :: 3.11
Requires-Dist: ipykernel (>=6.29.3,<7.0.0)
Requires-Dist: pandas (>=2.2.1,<3.0.0)
Requires-Dist: pytest (>=8.1.1,<9.0.0)
